pppssstest/__init__.py
pppssstest/__main__.py
pppssstest/pppssstest.py
pppssstest-1.14.dist-info/METADATA
pppssstest-1.14.dist-info/WHEEL
pppssstest-1.14.dist-info/entry_points.txt
pppssstest-1.14.dist-info/top_level.txt
pppssstest-1.14.dist-info/RECORD
